Orange3_Textable_Prototypes-0.32-py3.11-nspkg.pth
Orange3_Textable_Prototypes-0.32.data/data/help/orange3-textable-prototypes/.buildinfo
Orange3_Textable_Prototypes-0.32.data/data/help/orange3-textable-prototypes/.buildinfo.bak
Orange3_Textable_Prototypes-0.32.data/data/help/orange3-textable-prototypes/genindex.html
Orange3_Textable_Prototypes-0.32.data/data/help/orange3-textable-prototypes/index.html
Orange3_Textable_Prototypes-0.32.data/data/help/orange3-textable-prototypes/objects.inv
Orange3_Textable_Prototypes-0.32.data/data/help/orange3-textable-prototypes/search.html
Orange3_Textable_Prototypes-0.32.data/data/help/orange3-textable-prototypes/searchindex.js
Orange3_Textable_Prototypes-0.32.data/data/help/orange3-textable-prototypes/.doctrees/environment.pickle
Orange3_Textable_Prototypes-0.32.data/data/help/orange3-textable-prototypes/.doctrees/index.doctree
Orange3_Textable_Prototypes-0.32.data/data/help/orange3-textable-prototypes/.doctrees/widgets/18th_Century_Poetry.doctree
Orange3_Textable_Prototypes-0.32.data/data/help/orange3-textable-prototypes/.doctrees/widgets/CHILDES.doctree
Orange3_Textable_Prototypes-0.32.data/data/help/orange3-textable-prototypes/.doctrees/widgets/MovieReviews.doctree
Orange3_Textable_Prototypes-0.32.data/data/help/orange3-textable-prototypes/.doctrees/widgets/Scratodon.doctree
Orange3_Textable_Prototypes-0.32.data/data/help/orange3-textable-prototypes/.doctrees/widgets/SuperTextFiles.doctree
Orange3_Textable_Prototypes-0.32.data/data/help/orange3-textable-prototypes/.doctrees/widgets/Swiss_Law.doctree
Orange3_Textable_Prototypes-0.32.data/data/help/orange3-textable-prototypes/.doctrees/widgets/audioFile.doctree
Orange3_Textable_Prototypes-0.32.data/data/help/orange3-textable-prototypes/.doctrees/widgets/extractCSV.doctree
Orange3_Textable_Prototypes-0.32.data/data/help/orange3-textable-prototypes/.doctrees/widgets/gutenberg.doctree
Orange3_Textable_Prototypes-0.32.dist-info/LICENSE
Orange3_Textable_Prototypes-0.32.dist-info/METADATA
Orange3_Textable_Prototypes-0.32.dist-info/WHEEL
Orange3_Textable_Prototypes-0.32.dist-info/entry_points.txt
Orange3_Textable_Prototypes-0.32.dist-info/namespace_packages.txt
Orange3_Textable_Prototypes-0.32.dist-info/top_level.txt
Orange3_Textable_Prototypes-0.32.dist-info/RECORD
