Metadata-Version: 2.2
Name: Orange3-Textable-Prototypes
Version: 0.32
Summary: Additional widgets for the Textable add-on to Orange 3.
License: GPLv3
Keywords: text mining,text analysis,textable,orange3,orange3 add-on
License-File: LICENSE
Requires-Dist: Orange3
Requires-Dist: setuptools
Requires-Dist: future
Requires-Dist: LTTL>=2.1.0
Requires-Dist: Orange3-Textable>=3.2.5
Requires-Dist: gensim
Requires-Dist: lxa5crab
Requires-Dist: bs4
Requires-Dist: fuzzywuzzy
Requires-Dist: python-Levenshtein
Requires-Dist: requests
Requires-Dist: praw
Requires-Dist: spacy>=3.0
Requires-Dist: iso639-lang
Requires-Dist: filetype
Requires-Dist: pdfplumber
Requires-Dist: pymupdf
Requires-Dist: pytesseract
Requires-Dist: pillow
Requires-Dist: scikit-learn
Requires-Dist: gutenbergpy
Requires-Dist: filetype
Requires-Dist: pydub
Requires-Dist: SpeechRecognition
Requires-Dist: imdbpy
Requires-Dist: langdetect
Requires-Dist: deep_translator
Requires-Dist: Mastodon.py
Dynamic: description
Dynamic: keywords
Dynamic: license
Dynamic: requires-dist
Dynamic: summary
